[
  {
    "StudentID":67100420,
    "Name":"ณัฏฐนันท์ ณ ประสิทธิ์",
    "Email":"nattanan22520mpa@gmail.com",
    "Position":"นายกสโมสร",
    "Time":"2025-06-26 09:30:39"
  },
  {
    "StudentID":67100420,
    "Name":"ณัฏฐนันท์ ณ ประสิทธิ์",
    "Email":"nattanan22520mpa@gmail.com",
    "Position":"นายกสโมสร",
    "Time":"2025-06-26 09:37:36"
  },
  {
    "StudentID":67100420,
    "Name":"ณัฏฐนันท์ ณ ประสิทธิ์",
    "Email":"nattanan22520mpa@gmail.com",
    "Position":"นายกสโมสร",
    "Time":"2025-06-26 09:41:40"
  },
  {
    "StudentID":"67100420",
    "Name":"ณัฏฐนันท์ ณ ประสิทธิ์",
    "Email":"nattanan22520mpa@gmail.com",
    "Position":"นายกสโมสร",
    "Time":"2025-06-26 09:42:48"
  }
]